{
  "_meta": {
    "sources": [
      "loopback/common/models",
      "loopback/server/models",
      "../common/models",
      "./models"
    ]
  },
  "AccessToken": {
    "dataSource": "db",
    "public": false
  },
  "ACL": {
    "dataSource": "db",
    "public": false
  },
  "RoleMapping": {
    "dataSource": "db",
    "public": false
  },
  "Role": {
    "dataSource": "db",
    "public": false
  },
  "Report": {
    "dataSource": "yi-dev",
    "public": true
  },
  "PubWork": {
    "dataSource": "yi-dev",
    "public": true
  },
  "Category": {
    "dataSource": "yi-dev",
    "public": true
  },
  "Link": {
    "dataSource": "yi-dev",
    "public": false
  },
  "HistoryNode": {
    "dataSource": "yi-dev",
    "public": false
  },
  "Picture": {
    "dataSource": "yi-dev",
    "public": false
  },
  "Reporter": {
    "dataSource": "yi-dev",
    "public": true
  }
}
